CHANGES.txt
README.txt
bootstrap.py
buildout.cfg
setup.py
src/hurry/__init__.py
src/hurry.jqueryutils.egg-info/PKG-INFO
src/hurry.jqueryutils.egg-info/SOURCES.txt
src/hurry.jqueryutils.egg-info/dependency_links.txt
src/hurry.jqueryutils.egg-info/entry_points.txt
src/hurry.jqueryutils.egg-info/namespace_packages.txt
src/hurry.jqueryutils.egg-info/not-zip-safe
src/hurry.jqueryutils.egg-info/requires.txt
src/hurry.jqueryutils.egg-info/top_level.txt
src/hurry/jqueryutils/__init__.py
src/hurry/jqueryutils/_lib.py
src/hurry/jqueryutils/jqueryutils.txt
src/hurry/jqueryutils/tests.py
src/hurry/jqueryutils/jqueryutils-build/jquery.ddbelated.js
src/hurry/jqueryutils/jqueryutils-build/jquery.ddbelated.min.js
src/hurry/jqueryutils/jqueryutils-build/jquery.utils.css
src/hurry/jqueryutils/jqueryutils-build/jquery.utils.js
src/hurry/jqueryutils/jqueryutils-build/jquery.utils.lite.js
src/hurry/jqueryutils/jqueryutils-build/jquery.utils.lite.min.js
src/hurry/jqueryutils/jqueryutils-build/jquery.utils.min.js