Metadata-Version: 1.0
Name: hurry.jqueryutils
Version: 0.8.5.1
Summary: Hurry resource for JQuery-utils
Home-page: http://pypi.python.org/pypi/hurry.jqueryutils
Author: UNKNOWN
Author-email: UNKNOWN
License: MIT
Platform: UNKNOWN
Classifier: Programming Language :: Python
Classifier: Topic :: Software Development :: Libraries :: Python Modules
